{
  "main": {
    "id": "35465a53fd5406ed",
    "type": "split",
    "children": [
      {
        "id": "88f84665b8b7f2d6",
        "type": "tabs",
        "children": [
          {
            "id": "7ef0c961858dd1c2",
            "type": "leaf",
            "state": {
              "type": "markdown",
              "state": {
                "file": "Development/narrative-design/Proto-glod - script.md",
                "mode": "source",
                "source": false
              }
            }
          },
          {
            "id": "2414ff26cceab1a0",
            "type": "leaf",
            "state": {
              "type": "markdown",
              "state": {
                "file": "Process/journal.md",
                "mode": "source",
                "source": false
              }
            }
          },
          {
            "id": "34f74342e83ed79b",
            "type": "leaf",
            "state": {
              "type": "markdown",
              "state": {
                "file": "Process/why.md",
                "mode": "source",
                "source": false
              }
            }
          }
        ],
        "currentTab": 2
      }
    ],
    "direction": "vertical"
  },
  "left": {
    "id": "22c7346f66ad5ce3",
    "type": "split",
    "children": [
      {
        "id": "580e45a96919735b",
        "type": "tabs",
        "children": [
          {
            "id": "a5df250930f900e4",
            "type": "leaf",
            "state": {
              "type": "file-explorer",
              "state": {
                "sortOrder": "alphabetical"
              }
            }
          },
          {
            "id": "34078538fed247cb",
            "type": "leaf",
            "state": {
              "type": "search",
              "state": {
                "query": "",
                "matchingCase": false,
                "explainSearch": false,
                "collapseAll": false,
                "extraContext": false,
                "sortOrder": "alphabetical"
              }
            }
          },
          {
            "id": "bc80685d3db7738d",
            "type": "leaf",
            "state": {
              "type": "bookmarks",
              "state": {}
            }
          }
        ]
      }
    ],
    "direction": "horizontal",
    "width": 217.5
  },
  "right": {
    "id": "b613e2ffaa063ae3",
    "type": "split",
    "children": [
      {
        "id": "695748dd5631d1ee",
        "type": "tabs",
        "children": [
          {
            "id": "857e32e2911f595f",
            "type": "leaf",
            "state": {
              "type": "backlink",
              "state": {
                "file": "Process/why.md",
                "collapseAll": false,
                "extraContext": false,
                "sortOrder": "alphabetical",
                "showSearch": false,
                "searchQuery": "",
                "backlinkCollapsed": false,
                "unlinkedCollapsed": true
              }
            }
          },
          {
            "id": "b920d25e4940fac1",
            "type": "leaf",
            "state": {
              "type": "outgoing-link",
              "state": {
                "file": "Process/why.md",
                "linksCollapsed": false,
                "unlinkedCollapsed": true
              }
            }
          },
          {
            "id": "d903f513f382924a",
            "type": "leaf",
            "state": {
              "type": "tag",
              "state": {
                "sortOrder": "frequency",
                "useHierarchy": true
              }
            }
          },
          {
            "id": "9ac685bdceb7b494",
            "type": "leaf",
            "state": {
              "type": "outline",
              "state": {
                "file": "Process/why.md"
              }
            }
          }
        ]
      }
    ],
    "direction": "horizontal",
    "width": 300,
    "collapsed": true
  },
  "left-ribbon": {
    "hiddenItems": {
      "switcher:Open quick switcher": false,
      "graph:Open graph view": false,
      "canvas:Create new canvas": false,
      "daily-notes:Open today's daily note": false,
      "templates:Insert template": false,
      "command-palette:Open command palette": false
    }
  },
  "active": "34f74342e83ed79b",
  "lastOpenFiles": [
    "ProtoGlod_Play/Saved/WorldPartition/StreamingGeneration-PIE-2023.06.01-09.54.30.log",
    "ProtoGlod_Play/Intermediate/CachedAssetRegistry.bin.tmp",
    "ProtoGlod_Play/Intermediate/TurnkeyReport_0.log",
    "ProtoGlod_Play/Intermediate/DatasmithContentTemp",
    "ProtoGlod_Play/Saved/Logs/ProtoGlod_Play-backup-2023.05.31-18.37.30.log",
    "ProtoGlod_Play/Saved/Config/CrashReportClient/UECC-Windows-A5E6A24B40E4C240984D1E9F19F6D30B/CrashReportClient.ini",
    "ProtoGlod_Play/Saved/Config/CrashReportClient/UECC-Windows-A5E6A24B40E4C240984D1E9F19F6D30B",
    "ProtoGlod_Play/Content/__ExternalActors__/ThirdPerson/Maps/ThirdPersonMap/5/V8/O5ZVGLN6TBWVVO4IVV2BXR.uasset",
    "ProtoGlod_Play/Content/__ExternalActors__/ThirdPerson/Maps/ThirdPersonMap/5/V8",
    "ProtoGlod_Play/Content/__ExternalActors__/ThirdPerson/Maps/ThirdPersonMap/5/HE/3P0BGYGBILUGVTXIMPJBJJ.uasset",
    "ProtoGlod_Play/Content/__ExternalActors__/ThirdPerson/Maps/ThirdPersonMap/5/HE",
    "Process/journal.md",
    "Process/why.md",
    "Development/narrative-design/Proto-glod - script.md",
    "README.md",
    "Ideation/concept-art/Intrasensora_Layout_Sketch.jpeg",
    "Ideation/concept-art/Obsidian_sketches4.jpeg",
    "Ideation/concept-art/Mask_NoGo_Concept.jpeg",
    "Ideation/concept-art/IMG_0036.jpeg",
    "Ideation/concept-art/IMG_0035.jpeg",
    "Ideation/concept-art/IMG_0034.jpeg",
    "Ideation/concept-art/Obsidian__sketchCrop6.png",
    "Process/process-images/Cycle_Mesh_Sphere.png",
    "Ideation/concept-art/Obsidian__sketchCrop5.png",
    "Ideation/concept-art/Obsidian__sketchCrop4.png"
  ]
}